log9er/__about__.py
log9er/__init__.py
log9er/logger.py
log9er-0.1.1.dist-info/METADATA
log9er-0.1.1.dist-info/WHEEL
log9er-0.1.1.dist-info/licenses/LICENSE.txt
log9er-0.1.1.dist-info/RECORD
