Metadata-Version: 2.4
Name: log9er
Version: 0.1.1
Summary: Another simple logging wrapper.
Project-URL: Documentation, https://gitlab.com/joseph8th/log9er#readme
Project-URL: Issues, https://github.com/Joseph Edwards VIII/log9er/issues
Project-URL: Source, https://github.com/Joseph Edwards VIII/log9er
Author-email: Joseph Edwards VIII <jedwards8th@gmail.com>
License-Expression: MIT
License-File: LICENSE.txt
Classifier: Development Status :: 4 - Beta
Classifier: Programming Language :: Python
Classifier: Programming Language :: Python :: 3.8
Classifier: Programming Language :: Python :: 3.9
Classifier: Programming Language :: Python :: 3.10
Classifier: Programming Language :: Python :: 3.11
Classifier: Programming Language :: Python :: 3.12
Classifier: Programming Language :: Python :: Implementation :: CPython
Classifier: Programming Language :: Python :: Implementation :: PyPy
Requires-Python: >=3.10
Provides-Extra: test
Requires-Dist: pytest>=7.0; extra == 'test'
